bugbear.py
flake8_bugbear-24.10.31.dist-info/LICENSE
flake8_bugbear-24.10.31.dist-info/METADATA
flake8_bugbear-24.10.31.dist-info/WHEEL
flake8_bugbear-24.10.31.dist-info/entry_points.txt
flake8_bugbear-24.10.31.dist-info/top_level.txt
flake8_bugbear-24.10.31.dist-info/RECORD
