Metadata-Version: 2.1
Name: flake8-bugbear
Version: 24.10.31
Summary: A plugin for flake8 finding likely bugs and design problems in your program. Contains warnings that don't belong in pyflakes and pycodestyle.
Author-email: Łukasz Langa <lukasz@langa.pl>
License: MIT
Project-URL: Homepage, https://github.com/PyCQA/flake8-bugbear
Project-URL: Change Log, https://github.com/PyCQA/flake8-bugbear#change-log
Keywords: flake8,bugbear,bugs,pyflakes,pylint,linter,qa
Classifier: Development Status :: 5 - Production/Stable
Classifier: Environment :: Console
Classifier: Framework :: Flake8
Classifier: Intended Audience :: Developers
Classifier: License :: OSI Approved :: MIT License
Classifier: Operating System :: OS Independent
Classifier: Programming Language :: Python
Classifier: Programming Language :: Python :: 3
Classifier: Programming Language :: Python :: 3.8
Classifier: Programming Language :: Python :: 3.9
Classifier: Programming Language :: Python :: 3.10
Classifier: Programming Language :: Python :: 3.11
Classifier: Programming Language :: Python :: 3.12
Classifier: Programming Language :: Python :: 3.13
Classifier: Programming Language :: Python :: 3 :: Only
Classifier: Topic :: Software Development :: Libraries :: Python Modules
Classifier: Topic :: Software Development :: Quality Assurance
Requires-Python: >=3.8.1
License-File: LICENSE
Requires-Dist: flake8>=6.0.0
Requires-Dist: attrs>=22.2.0
Provides-Extra: dev
Requires-Dist: tox; extra == "dev"
Requires-Dist: coverage; extra == "dev"
Requires-Dist: hypothesis; extra == "dev"
Requires-Dist: hypothesmith>=0.2; extra == "dev"
Requires-Dist: pre-commit; extra == "dev"
Requires-Dist: pytest; extra == "dev"
